{"commitInfo":{"timestamp":1743785031173,"operation":"WRITE","operationParameters":{"mode":"Append","partitionBy":"[]"},"readVersion":17,"isolationLevel":"Serializable","isBlindAppend":true,"operationMetrics":{"numFiles":"24","numOutputRows":"813","numOutputBytes":"94080"},"engineInfo":"Apache-Spark/3.4.0 Delta-Lake/2.4.0","txnId":"840919ea-1b51-44a1-b95e-b2cc34453e74"}}
{"add":{"path":"part-00000-b4faa487-8893-415d-b091-6849a1c521aa-c000.snappy.parquet","partitionValues":{},"size":3920,"modificationTime":1743785031117,"dataChange":true,"stats":"{\"numRecords\":33,\"minValues\":{},\"maxValues\":{},\"nullCount\":{\"appid\":33,\"name\":33,\"type\":33,\"developers\":33,\"publishers\":33,\"release_date\":33,\"supported_languages\":33,\"categories\":33,\"genres\":33,\"platforms\":33,\"price\":33,\"tags\":33,\"current_player_count\":33,\"timestamp\":33}}"}}
{"add":{"path":"part-00001-4dae2a92-1b8b-4071-bde8-537c5a41b5dc-c000.snappy.parquet","partitionValues":{},"size":3920,"modificationTime":1743785031117,"dataChange":true,"stats":"{\"numRecords\":33,\"minValues\":{},\"maxValues\":{},\"nullCount\":{\"appid\":33,\"name\":33,\"type\":33,\"developers\":33,\"publishers\":33,\"release_date\":33,\"supported_languages\":33,\"categories\":33,\"genres\":33,\"platforms\":33,\"price\":33,\"tags\":33,\"current_player_count\":33,\"timestamp\":33}}"}}
{"add":{"path":"part-00002-20c74df5-eaec-46c1-a635-741959a4f538-c000.snappy.parquet","partitionValues":{},"size":3920,"modificationTime":1743785031117,"dataChange":true,"stats":"{\"numRecords\":33,\"minValues\":{},\"maxValues\":{},\"nullCount\":{\"appid\":33,\"name\":33,\"type\":33,\"developers\":33,\"publishers\":33,\"release_date\":33,\"supported_languages\":33,\"categories\":33,\"genres\":33,\"platforms\":33,\"price\":33,\"tags\":33,\"current_player_count\":33,\"timestamp\":33}}"}}
{"add":{"path":"part-00003-e6dca150-5890-41de-b92c-40e9e3e18faf-c000.snappy.parquet","partitionValues":{},"size":3920,"modificationTime":1743785031117,"dataChange":true,"stats":"{\"numRecords\":33,\"minValues\":{},\"maxValues\":{},\"nullCount\":{\"appid\":33,\"name\":33,\"type\":33,\"developers\":33,\"publishers\":33,\"release_date\":33,\"supported_languages\":33,\"categories\":33,\"genres\":33,\"platforms\":33,\"price\":33,\"tags\":33,\"current_player_count\":33,\"timestamp\":33}}"}}
{"add":{"path":"part-00004-9a361463-7708-4e78-bc7a-b658cd891384-c000.snappy.parquet","partitionValues":{},"size":3920,"modificationTime":1743785031117,"dataChange":true,"stats":"{\"numRecords\":33,\"minValues\":{},\"maxValues\":{},\"nullCount\":{\"appid\":33,\"name\":33,\"type\":33,\"developers\":33,\"publishers\":33,\"release_date\":33,\"supported_languages\":33,\"categories\":33,\"genres\":33,\"platforms\":33,\"price\":33,\"tags\":33,\"current_player_count\":33,\"timestamp\":33}}"}}
{"add":{"path":"part-00005-9e74f3b4-551d-439d-bcbb-c0b42dd63695-c000.snappy.parquet","partitionValues":{},"size":3920,"modificationTime":1743785031117,"dataChange":true,"stats":"{\"numRecords\":33,\"minValues\":{},\"maxValues\":{},\"nullCount\":{\"appid\":33,\"name\":33,\"type\":33,\"developers\":33,\"publishers\":33,\"release_date\":33,\"supported_languages\":33,\"categories\":33,\"genres\":33,\"platforms\":33,\"price\":33,\"tags\":33,\"current_player_count\":33,\"timestamp\":33}}"}}
{"add":{"path":"part-00006-a9ad048d-4224-4f37-966b-78fcb9e4f404-c000.snappy.parquet","partitionValues":{},"size":3920,"modificationTime":1743785031117,"dataChange":true,"stats":"{\"numRecords\":33,\"minValues\":{},\"maxValues\":{},\"nullCount\":{\"appid\":33,\"name\":33,\"type\":33,\"developers\":33,\"publishers\":33,\"release_date\":33,\"supported_languages\":33,\"categories\":33,\"genres\":33,\"platforms\":33,\"price\":33,\"tags\":33,\"current_player_count\":33,\"timestamp\":33}}"}}
{"add":{"path":"part-00007-03ca7eb8-5e13-4eee-b592-1a99e810a0b7-c000.snappy.parquet","partitionValues":{},"size":3920,"modificationTime":1743785031117,"dataChange":true,"stats":"{\"numRecords\":33,\"minValues\":{},\"maxValues\":{},\"nullCount\":{\"appid\":33,\"name\":33,\"type\":33,\"developers\":33,\"publishers\":33,\"release_date\":33,\"supported_languages\":33,\"categories\":33,\"genres\":33,\"platforms\":33,\"price\":33,\"tags\":33,\"current_player_count\":33,\"timestamp\":33}}"}}
{"add":{"path":"part-00008-d8cd2aa7-3674-44de-ac1a-1c59217e5391-c000.snappy.parquet","partitionValues":{},"size":3920,"modificationTime":1743785031117,"dataChange":true,"stats":"{\"numRecords\":33,\"minValues\":{},\"maxValues\":{},\"nullCount\":{\"appid\":33,\"name\":33,\"type\":33,\"developers\":33,\"publishers\":33,\"release_date\":33,\"supported_languages\":33,\"categories\":33,\"genres\":33,\"platforms\":33,\"price\":33,\"tags\":33,\"current_player_count\":33,\"timestamp\":33}}"}}
{"add":{"path":"part-00009-92aa9973-628b-426d-84f4-62fbb4740f54-c000.snappy.parquet","partitionValues":{},"size":3920,"modificationTime":1743785031117,"dataChange":true,"stats":"{\"numRecords\":33,\"minValues\":{},\"maxValues\":{},\"nullCount\":{\"appid\":33,\"name\":33,\"type\":33,\"developers\":33,\"publishers\":33,\"release_date\":33,\"supported_languages\":33,\"categories\":33,\"genres\":33,\"platforms\":33,\"price\":33,\"tags\":33,\"current_player_count\":33,\"timestamp\":33}}"}}
{"add":{"path":"part-00010-e2b06d2c-b89c-413f-b3d4-e15a294c30f3-c000.snappy.parquet","partitionValues":{},"size":3920,"modificationTime":1743785031117,"dataChange":true,"stats":"{\"numRecords\":33,\"minValues\":{},\"maxValues\":{},\"nullCount\":{\"appid\":33,\"name\":33,\"type\":33,\"developers\":33,\"publishers\":33,\"release_date\":33,\"supported_languages\":33,\"categories\":33,\"genres\":33,\"platforms\":33,\"price\":33,\"tags\":33,\"current_player_count\":33,\"timestamp\":33}}"}}
{"add":{"path":"part-00011-8926d8ea-ad32-4a51-8f2c-d6735dd34d04-c000.snappy.parquet","partitionValues":{},"size":3920,"modificationTime":1743785031117,"dataChange":true,"stats":"{\"numRecords\":33,\"minValues\":{},\"maxValues\":{},\"nullCount\":{\"appid\":33,\"name\":33,\"type\":33,\"developers\":33,\"publishers\":33,\"release_date\":33,\"supported_languages\":33,\"categories\":33,\"genres\":33,\"platforms\":33,\"price\":33,\"tags\":33,\"current_player_count\":33,\"timestamp\":33}}"}}
{"add":{"path":"part-00012-37a12071-661d-48c3-852b-89871a9bb56b-c000.snappy.parquet","partitionValues":{},"size":3920,"modificationTime":1743785031117,"dataChange":true,"stats":"{\"numRecords\":33,\"minValues\":{},\"maxValues\":{},\"nullCount\":{\"appid\":33,\"name\":33,\"type\":33,\"developers\":33,\"publishers\":33,\"release_date\":33,\"supported_languages\":33,\"categories\":33,\"genres\":33,\"platforms\":33,\"price\":33,\"tags\":33,\"current_player_count\":33,\"timestamp\":33}}"}}
{"add":{"path":"part-00013-fa127be8-fa01-41dd-ad4f-e2104a067549-c000.snappy.parquet","partitionValues":{},"size":3920,"modificationTime":1743785031117,"dataChange":true,"stats":"{\"numRecords\":33,\"minValues\":{},\"maxValues\":{},\"nullCount\":{\"appid\":33,\"name\":33,\"type\":33,\"developers\":33,\"publishers\":33,\"release_date\":33,\"supported_languages\":33,\"categories\":33,\"genres\":33,\"platforms\":33,\"price\":33,\"tags\":33,\"current_player_count\":33,\"timestamp\":33}}"}}
{"add":{"path":"part-00014-eb01e5b5-9622-4267-b756-b936d03ee281-c000.snappy.parquet","partitionValues":{},"size":3920,"modificationTime":1743785031117,"dataChange":true,"stats":"{\"numRecords\":33,\"minValues\":{},\"maxValues\":{},\"nullCount\":{\"appid\":33,\"name\":33,\"type\":33,\"developers\":33,\"publishers\":33,\"release_date\":33,\"supported_languages\":33,\"categories\":33,\"genres\":33,\"platforms\":33,\"price\":33,\"tags\":33,\"current_player_count\":33,\"timestamp\":33}}"}}
{"add":{"path":"part-00015-82c9c894-5cfa-44bb-85de-b89030b4a7ae-c000.snappy.parquet","partitionValues":{},"size":3920,"modificationTime":1743785031117,"dataChange":true,"stats":"{\"numRecords\":33,\"minValues\":{},\"maxValues\":{},\"nullCount\":{\"appid\":33,\"name\":33,\"type\":33,\"developers\":33,\"publishers\":33,\"release_date\":33,\"supported_languages\":33,\"categories\":33,\"genres\":33,\"platforms\":33,\"price\":33,\"tags\":33,\"current_player_count\":33,\"timestamp\":33}}"}}
{"add":{"path":"part-00016-d0edf84f-257a-42d4-b200-fff43e66d7d4-c000.snappy.parquet","partitionValues":{},"size":3920,"modificationTime":1743785031117,"dataChange":true,"stats":"{\"numRecords\":33,\"minValues\":{},\"maxValues\":{},\"nullCount\":{\"appid\":33,\"name\":33,\"type\":33,\"developers\":33,\"publishers\":33,\"release_date\":33,\"supported_languages\":33,\"categories\":33,\"genres\":33,\"platforms\":33,\"price\":33,\"tags\":33,\"current_player_count\":33,\"timestamp\":33}}"}}
{"add":{"path":"part-00017-59bc7c5f-f750-4744-992b-6d197dcd9b81-c000.snappy.parquet","partitionValues":{},"size":3920,"modificationTime":1743785031117,"dataChange":true,"stats":"{\"numRecords\":33,\"minValues\":{},\"maxValues\":{},\"nullCount\":{\"appid\":33,\"name\":33,\"type\":33,\"developers\":33,\"publishers\":33,\"release_date\":33,\"supported_languages\":33,\"categories\":33,\"genres\":33,\"platforms\":33,\"price\":33,\"tags\":33,\"current_player_count\":33,\"timestamp\":33}}"}}
{"add":{"path":"part-00018-6b506e64-19c7-4503-9f2a-3c8f0b445faf-c000.snappy.parquet","partitionValues":{},"size":3920,"modificationTime":1743785031117,"dataChange":true,"stats":"{\"numRecords\":33,\"minValues\":{},\"maxValues\":{},\"nullCount\":{\"appid\":33,\"name\":33,\"type\":33,\"developers\":33,\"publishers\":33,\"release_date\":33,\"supported_languages\":33,\"categories\":33,\"genres\":33,\"platforms\":33,\"price\":33,\"tags\":33,\"current_player_count\":33,\"timestamp\":33}}"}}
{"add":{"path":"part-00019-6971b21d-f599-43d2-a93e-955395a4a3bb-c000.snappy.parquet","partitionValues":{},"size":3920,"modificationTime":1743785031117,"dataChange":true,"stats":"{\"numRecords\":33,\"minValues\":{},\"maxValues\":{},\"nullCount\":{\"appid\":33,\"name\":33,\"type\":33,\"developers\":33,\"publishers\":33,\"release_date\":33,\"supported_languages\":33,\"categories\":33,\"genres\":33,\"platforms\":33,\"price\":33,\"tags\":33,\"current_player_count\":33,\"timestamp\":33}}"}}
{"add":{"path":"part-00020-0f5e1e1e-1330-4f5b-9d39-80cc6aee3020-c000.snappy.parquet","partitionValues":{},"size":3920,"modificationTime":1743785031117,"dataChange":true,"stats":"{\"numRecords\":33,\"minValues\":{},\"maxValues\":{},\"nullCount\":{\"appid\":33,\"name\":33,\"type\":33,\"developers\":33,\"publishers\":33,\"release_date\":33,\"supported_languages\":33,\"categories\":33,\"genres\":33,\"platforms\":33,\"price\":33,\"tags\":33,\"current_player_count\":33,\"timestamp\":33}}"}}
{"add":{"path":"part-00021-11b458cd-42bb-4ad4-8f1b-9c1d46a155fc-c000.snappy.parquet","partitionValues":{},"size":3920,"modificationTime":1743785031117,"dataChange":true,"stats":"{\"numRecords\":33,\"minValues\":{},\"maxValues\":{},\"nullCount\":{\"appid\":33,\"name\":33,\"type\":33,\"developers\":33,\"publishers\":33,\"release_date\":33,\"supported_languages\":33,\"categories\":33,\"genres\":33,\"platforms\":33,\"price\":33,\"tags\":33,\"current_player_count\":33,\"timestamp\":33}}"}}
{"add":{"path":"part-00022-f5f2360e-9658-43bd-ba8d-0a4b8f81933d-c000.snappy.parquet","partitionValues":{},"size":3920,"modificationTime":1743785031117,"dataChange":true,"stats":"{\"numRecords\":33,\"minValues\":{},\"maxValues\":{},\"nullCount\":{\"appid\":33,\"name\":33,\"type\":33,\"developers\":33,\"publishers\":33,\"release_date\":33,\"supported_languages\":33,\"categories\":33,\"genres\":33,\"platforms\":33,\"price\":33,\"tags\":33,\"current_player_count\":33,\"timestamp\":33}}"}}
{"add":{"path":"part-00023-d14ae5c2-8598-4fc6-9707-3c40c9063320-c000.snappy.parquet","partitionValues":{},"size":3920,"modificationTime":1743785031117,"dataChange":true,"stats":"{\"numRecords\":54,\"minValues\":{},\"maxValues\":{},\"nullCount\":{\"appid\":54,\"name\":54,\"type\":54,\"developers\":54,\"publishers\":54,\"release_date\":54,\"supported_languages\":54,\"categories\":54,\"genres\":54,\"platforms\":54,\"price\":54,\"tags\":54,\"current_player_count\":54,\"timestamp\":54}}"}}
